{
  "$defs": {
    "JobStatus": {
      "enum": [
        "pending",
        "in_progress",
        "completed",
        "failed"
      ],
      "title": "JobStatus",
      "type": "string"
    }
  },
  "properties": {
    "job_id": {
      "title": "Job Id",
      "type": "string"
    },
    "status": {
      "$ref": "#/$defs/JobStatus"
    },
    "message": {
      "title": "Message",
      "type": "string"
    },
    "created_at": {
      "format": "date-time",
      "title": "Created At",
      "type": "string"
    }
  },
  "required": [
    "job_id",
    "status",
    "message",
    "created_at"
  ],
  "title": "ScrapeResponse",
  "type": "object"
}